pywabot/__init__.py
pywabot/bot.py
pywabot/exceptions.py
pywabot/logging.py
pywabot/types.py
pywabot/internal/__init__.py
pywabot/internal/api_client.py
pywabot/internal/websocket_client.py
pywabot-0.3.9.dist-info/licenses/LICENSE
pywabot-0.3.9.dist-info/METADATA
pywabot-0.3.9.dist-info/WHEEL
pywabot-0.3.9.dist-info/top_level.txt
pywabot-0.3.9.dist-info/RECORD
