Metadata-Version: 2.4
Name: pywabot
Version: 0.3.9
Summary: An asynchronous Python wrapper for the Baileys WhatsApp API.
License: MIT
Requires-Python: >=3.8
License-File: LICENSE
Requires-Dist: httpx
Requires-Dist: websockets
Requires-Dist: python-dotenv
Provides-Extra: dev
Requires-Dist: pytest; extra == "dev"
Requires-Dist: pytest-asyncio; extra == "dev"
Requires-Dist: pytest-mock; extra == "dev"
Dynamic: license-file
